[
    {
        "question": "Which of the following is not a valid TypeScript type?",
        "answers": [
            "string",
            "int",
            "number",
            "boolean",
            "any",
            "void"
        ],
        "correctAnswer": [1, 4, 5],
        "multi": true
    },
    {
        "question": "What is the purpose of the 'provide' and 'inject' feature in Vue.js?",
        "answers": [
            "For server-side rendering",
            "For passing data down the component tree without props",
            "For managing global state",
            "For fun"
        ],
        "correctAnswer": [1],
        "multi": false
    },
    {
        "question": "What assertion method from the \"@vue/test-utils\" library will you use to test if an element has one of the following style properties attached to it or not - \"display: none,\" \"visibility: hidden,\" \"opacity :0\"?",
        "answers": [
            "hasStyle",
            "hasAttribute",
            "isVisible",
            "isHidden"
        ],
        "correctAnswer": [2],
        "multi": false
    },
    {
        "question": "Which of the directives below provide a two-way binding?",
        "answers": [
            "v-model",
            "v-bind",
            "v-on",
            "v-cloak"
        ],
        "correctAnswer": [0],
        "multi": false
    },
    {
        "question": "Which of the following directives is to used for attaching event listeners that invoke methods?",
        "answers": [
            "@click",
            "v-on",
            "v-model",
            "v-cloak"
        ],
        "correctAnswer": [0],
        "multi": false
    },
    {
        "question": "What is the purpose of the 'name' property in a Vue.js component?",
        "answers": [
            "To specify the name used in the DOM",
            "To define the component's name for recursive calls",
            "To set the name attribute on the root element",
            "To identify the component in Vue Devtools"
        ],
        "correctAnswer": [
            1, 3
        ],
        "multi": true
    },
    {
        "question": "What is the purpose of the 'nextTick' method in Vue.js?",
        "answers": [
            "To delay the execution of a function until the next DOM update cycle",
            "To navigate to the next route in Vue Router",
            "To proceed to the next item in a v-for loop",
            "To update data properties in the next component update"
        ],
        "correctAnswer": [0],
        "multi": false
    }
]